b2py/__init__.py
b2py/b2.py
b2py/constants.py
b2py/utils.py
backblazeb2-0.1.9.dist-info/LICENSE
backblazeb2-0.1.9.dist-info/METADATA
backblazeb2-0.1.9.dist-info/WHEEL
backblazeb2-0.1.9.dist-info/top_level.txt
backblazeb2-0.1.9.dist-info/RECORD
